scidat/__init__.py
scidat/__main__.py
scidat/annotate.py
scidat/api.py
scidat/download.py
scidat-1.0.6.data/data/LICENSE
scidat-1.0.6.data/data/clinical.txt
scidat-1.0.6.data/data/d3f73c0f-d518-4e91-b038-a4360495ee27.htseq.counts.tsv
scidat-1.0.6.data/data/gdc-client
scidat-1.0.6.data/data/jhu-usc.edu_KIRC.HumanMethylation450.6.lvl-3.TCGA-CZ-5989-01A-11D-1670-05.gdc_hg38.txt
scidat-1.0.6.data/data/manifest.tsv
scidat-1.0.6.data/data/mutation_TCGA-A3-3308_20200410.tsv
scidat-1.0.6.data/data/mutation_TCGA-KN-8422_20200410.tsv
scidat-1.0.6.data/data/sample_sheet.txt
scidat-1.0.6.data/data/tcga_hsapiens_gene_ensembl-GRCh38.p13.csv
scidat-1.0.6.dist-info/LICENSE
scidat-1.0.6.dist-info/METADATA
scidat-1.0.6.dist-info/WHEEL
scidat-1.0.6.dist-info/entry_points.txt
scidat-1.0.6.dist-info/top_level.txt
scidat-1.0.6.dist-info/RECORD
