Metadata-Version: 2.1
Name: scidat
Version: 1.0.6
Summary: Download-Annotate-TCGA: Facilitates the download of data and annotation with metadata from TCGA
Home-page: https://github.com/ArianeMora/scidat
Author: Ariane Mora
Author-email: ariane.n.mora@gmail.com
License: GPL3
Project-URL: Bug Tracker, https://github.com/ArianeMora/scidat/issues
Project-URL: Documentation, https://github.com/ArianeMora/scidat
Project-URL: Source Code, https://github.com/ArianeMora/scidat
Keywords: annotation
Platform: UNKNOWN
Classifier: Intended Audience :: Science/Research
Classifier: License :: OSI Approved :: GNU General Public License v3 (GPLv3)
Classifier: Natural Language :: English
Classifier: Operating System :: OS Independent
Classifier: Programming Language :: Python :: 3.6
Classifier: Programming Language :: Python :: 3.7
Classifier: Programming Language :: Python :: 3.8
Classifier: Topic :: Scientific/Engineering :: Bio-Informatics
Requires-Python: >=3.6
Requires-Dist: sciutil
Requires-Dist: pandas
Requires-Dist: numpy
Requires-Dist: scibiomart
Requires-Dist: sciviso (>=1.0.1)
